{
  "meta": {
    "build": {
      "build-date": "2021-12-27",
      "ci-build-number": "1.0.181",
      "ci-project": "cityofsanmateo/law-xml",
      "codified-date": "2022-01-14",
      "platform": {
        "reproducible": "false",
        "version": "2.5.4"
      },
      "repositories": [
        {
          "commit": "0fa9a1d333c9aa37da2bca97a4369dc762e02937",
          "name": "cityofsanmateo/law-xml"
        },
        {
          "commit": "d9815bb9fa71dd7bcab9d8837fa3190b649feaf6",
          "name": "cityofsanmateo/law-xml-codified-preview"
        }
      ]
    },
    "canonical-urls": {
      "html": "https://sanmateo.ca.us.open.law",
      "html-bulk": "https://github.com/cityofsanmateo/law-html",
      "static-assets": "https://github.com/openlawlibrary/law-static-assets",
      "xml-bulk": "https://github.com/cityofsanmateo/law-xml"
    },
    "contact": {
      "email": "help@openlawlib.org"
    },
    "description": "Browse the laws and code of San Mateo",
    "history-start": "2018-03-05"
  }
}